mfd_typing/__init__.py
mfd_typing/cpu_values.py
mfd_typing/data_structures.py
mfd_typing/dataclass_utils.py
mfd_typing/driver_info.py
mfd_typing/exceptions.py
mfd_typing/mac_address.py
mfd_typing/network_interface.py
mfd_typing/os_values.py
mfd_typing/pci_address.py
mfd_typing/pci_device.py
mfd_typing/utils.py
mfd_typing/vendor_device_id.py
mfd_typing-1.24.0.dist-info/licenses/AUTHORS.md
mfd_typing-1.24.0.dist-info/licenses/LICENSE.md
mfd_typing-1.24.0.dist-info/METADATA
mfd_typing-1.24.0.dist-info/WHEEL
mfd_typing-1.24.0.dist-info/top_level.txt
mfd_typing-1.24.0.dist-info/RECORD
