Metadata-Version: 2.4
Name: mfd-typing
Version: 1.24.0
Summary: Module containing common data structures and utilities shared between MFD modules.
Project-URL: Homepage, https://github.com/intel/mfd
Project-URL: Repository, https://github.com/intel/mfd-typing
Project-URL: Issues, https://github.com/intel/mfd-typing/issues
Project-URL: Changelog, https://github.com/intel/mfd-typing/blob/main/CHANGELOG.md
Requires-Python: <3.14,>=3.10
License-File: LICENSE.md
License-File: AUTHORS.md
Requires-Dist: netaddr<1.0,>=0.8.0
Requires-Dist: python-generate-mac>=1.3.1
Dynamic: license-file
